{
    "key": "group_59e4a6896f40b",
    "title": "Block. Back Button",
    "fields": [
        {
            "key": "field_59e4a695ec7de",
            "label": "Specific",
            "name": "",
            "type": "tab",
            "instructions": "",
            "required": 0,
            "conditional_logic": 0,
            "wrapper": {
                "width": "",
                "class": "",
                "id": ""
            },
            "placement": "top",
            "endpoint": 0
        },
        {
            "key": "field_59e4a6a1ec7df",
            "label": "Overview",
            "name": "",
            "type": "message",
            "instructions": "",
            "required": 0,
            "conditional_logic": 0,
            "wrapper": {
                "width": "",
                "class": "acf-field--full-width",
                "id": ""
            },
            "message": "<img class=\"acf-img\" src=\"https:\/\/s3-us-west-2.amazonaws.com\/flothemes-dashboard-images\/lovely2\/block-back-button.overview.jpg\" \/>",
            "new_lines": "wpautop",
            "esc_html": 0
        },
        {
            "key": "field_59e4a6bdec7e0",
            "label": "1. Elements Color",
            "name": "elements_color",
            "type": "flo_color_picker",
            "instructions": "",
            "required": 0,
            "conditional_logic": 0,
            "wrapper": {
                "width": "",
                "class": "",
                "id": ""
            },
            "color_options_prefix": "flo-color-",
            "default_color_id": 1,
            "default_value": ""
        },
        {
            "key": "field_59e4a6e9ec7e1",
            "label": "2. Label",
            "name": "label",
            "type": "text",
            "instructions": "",
            "required": 0,
            "conditional_logic": 0,
            "wrapper": {
                "width": "",
                "class": "",
                "id": ""
            },
            "default_value": "BACK",
            "placeholder": "",
            "prepend": "",
            "append": "",
            "maxlength": ""
        },
        {
            "key": "field_59e4a701ec7e2",
            "label": "2.1. Label Font",
            "name": "label_font",
            "type": "font_style_select",
            "instructions": "Default: Call to Action 1",
            "required": 0,
            "conditional_logic": 0,
            "wrapper": {
                "width": "",
                "class": "",
                "id": ""
            },
            "default_css_selectors": "",
            "active_css_selectors": "",
            "hover_css_selectors": "",
            "typography_option_name": "",
            "default_typography_style": "call_to_action_1"
        },
        {
            "key": "field_59e4a723ec7e3",
            "label": "3. Custom Link",
            "name": "custom_link",
            "type": "text",
            "instructions": "Note: while this field is empty, the button will link to browsers previous location.",
            "required": 0,
            "conditional_logic": 0,
            "wrapper": {
                "width": "",
                "class": "",
                "id": ""
            },
            "default_value": "",
            "placeholder": "",
            "prepend": "",
            "append": "",
            "maxlength": ""
        },
        {
            "key": "field_59e4a755ec7e4",
            "label": "Additional",
            "name": "additional",
            "type": "clone",
            "instructions": "",
            "required": 0,
            "conditional_logic": 0,
            "wrapper": {
                "width": "",
                "class": "",
                "id": ""
            },
            "clone": [
                "group_58eb425e82b8c"
            ],
            "display": "seamless",
            "layout": "block",
            "prefix_label": 0,
            "prefix_name": 0
        }
    ],
    "location": [
        [
            {
                "param": "post_type",
                "operator": "==",
                "value": "post"
            }
        ]
    ],
    "menu_order": 0,
    "position": "normal",
    "style": "default",
    "label_placement": "top",
    "instruction_placement": "label",
    "hide_on_screen": "",
    "active": 0,
    "description": "",
    "modified": 1508157630
}